alter_sdk/__init__.py
alter_sdk/client.py
alter_sdk/exceptions.py
alter_sdk/models.py
alter_sdk/providers/__init__.py
alter_sdk/providers/base.py
alter_sdk/providers/enums.py
alter_sdk/providers/generic.py
alter_sdk/providers/github.py
alter_sdk/providers/google.py
alter_sdk/providers/registry.py
alter_sdk/utils/__init__.py
alter_sdk/utils/http_client.py
alter_sdk-0.1.1.dist-info/METADATA
alter_sdk-0.1.1.dist-info/WHEEL
alter_sdk-0.1.1.dist-info/RECORD
