Metadata-Version: 2.4
Name: alter-sdk
Version: 0.1.1
Summary: Alter Vault Python SDK - OAuth token management with policy enforcement
Keywords: oauth,tokens,security,policy,vault
Author: Alter Team
Author-email: founders@alterai.dev
Requires-Python: >=3.11,<4.0
Classifier: Development Status :: 3 - Alpha
Classifier: Intended Audience :: Developers
Classifier: License :: OSI Approved :: MIT License
Classifier: Programming Language :: Python :: 3
Classifier: Programming Language :: Python :: 3.11
Classifier: Programming Language :: Python :: 3.12
Classifier: Programming Language :: Python :: 3.13
Classifier: Programming Language :: Python :: 3.14
Provides-Extra: all
Provides-Extra: github
Provides-Extra: google
Requires-Dist: PyGithub (>=2.1.0,<3.0.0) ; extra == "github" or extra == "all"
Requires-Dist: google-api-python-client (>=2.100.0,<3.0.0) ; extra == "google" or extra == "all"
Requires-Dist: google-auth (>=2.23.0,<3.0.0) ; extra == "google" or extra == "all"
Requires-Dist: google-auth-httplib2 (>=0.1.1,<0.2.0) ; extra == "google" or extra == "all"
Requires-Dist: httpx[http2] (>=0.25.0,<0.26.0)
Requires-Dist: pydantic (>=2.5.0,<3.0.0)
Project-URL: Homepage, https://alterai.dev
